ncbi_cluster_tracker/__init__.py
ncbi_cluster_tracker/cli.py
ncbi_cluster_tracker/cluster.py
ncbi_cluster_tracker/download.py
ncbi_cluster_tracker/logger.py
ncbi_cluster_tracker/main.py
ncbi_cluster_tracker/query.py
ncbi_cluster_tracker/report.py
ncbi_cluster_tracker-0.3.0.dist-info/LICENSE
ncbi_cluster_tracker-0.3.0.dist-info/METADATA
ncbi_cluster_tracker-0.3.0.dist-info/WHEEL
ncbi_cluster_tracker-0.3.0.dist-info/entry_points.txt
ncbi_cluster_tracker-0.3.0.dist-info/RECORD
