Metadata-Version: 2.3
Name: ncbi-cluster-tracker
Version: 0.3.0
Summary: Create standalone HTML reports for tracking SNP clusters within NCBI Pathogen Detection
License: GPL-3.0
Author: Sam Baird
Author-email: sam.baird@state.co.us
Requires-Python: >=3.12,<4.0
Classifier: License :: OSI Approved :: GNU General Public License v3 (GPLv3)
Classifier: Programming Language :: Python :: 3
Classifier: Programming Language :: Python :: 3.12
Classifier: Programming Language :: Python :: 3.13
Requires-Dist: arakawa (>=0.0.16,<0.0.17)
Requires-Dist: db-dtypes (>=1.4.2,<2.0.0)
Requires-Dist: dendropy (>=5.0.1,<6.0.0)
Requires-Dist: google-cloud-bigquery[pandas] (>=3.31.0,<4.0.0)
Requires-Dist: matplotlib (>=3.10.1,<4.0.0)
Requires-Dist: mypy (>=1.17.1,<2.0.0)
Requires-Dist: pandas (>=2.2.3,<3.0.0)
Requires-Dist: pandas-stubs (>=2.3.0.250703,<3.0.0.0)
Requires-Dist: plotly (>=5.2.4,<6.0.0)
Requires-Dist: requests (>=2.32.3,<3.0.0)
Requires-Dist: tqdm (>=4.67.1,<5.0.0)
Requires-Dist: types-tqdm (>=4.67.0.20250809,<5.0.0.0)
